celldict/__init__.py
celldict/main.py
celldict-2.0.1.dist-info/LICENSE
celldict-2.0.1.dist-info/METADATA
celldict-2.0.1.dist-info/WHEEL
celldict-2.0.1.dist-info/top_level.txt
celldict-2.0.1.dist-info/RECORD
