Metadata-Version: 2.1
Name: celldict
Version: 2.0.1
Summary: Python 简洁快速的保存和读取变量, 方便的版本控制!
Home-page: https://github.com/EVA-JianJun/celldict
Author: jianjun
Author-email: 910667956@qq.com
License-File: LICENSE
